probeye/__init__.py
probeye/_setup_cfg.py
probeye/probeye.txt
probeye/subroutines.py
probeye/definition/__init__.py
probeye/definition/correlation_model.py
probeye/definition/distribution.py
probeye/definition/experiment.py
probeye/definition/forward_model.py
probeye/definition/inference_problem.py
probeye/definition/inverse_problem.py
probeye/definition/likelihood_model.py
probeye/definition/parameter.py
probeye/definition/prior.py
probeye/definition/sensor.py
probeye/inference/__init__.py
probeye/inference/solver.py
probeye/inference/dynesty/__init__.py
probeye/inference/dynesty/solver.py
probeye/inference/emcee/__init__.py
probeye/inference/emcee/solver.py
probeye/inference/scipy/__init__.py
probeye/inference/scipy/distributions.py
probeye/inference/scipy/likelihood_models.py
probeye/inference/scipy/priors.py
probeye/inference/scipy/solver.py
probeye/ontology/__init__.py
probeye/ontology/knowledge_graph_export.py
probeye/ontology/parameter_estimation_ontology.owl
probeye/postprocessing/__init__.py
probeye/postprocessing/sampling_plots.py
tests/__init__.py
tests/integration_tests/__init__.py
tests/integration_tests/subroutines.py
tests/integration_tests/tests_with_correlation/__init__.py
tests/integration_tests/tests_with_correlation/test_1D_1D_correlation_additive_model_error_1std.py
tests/integration_tests/tests_with_correlation/test_1D_1D_correlation_additive_model_error_2std.py
tests/integration_tests/tests_with_correlation/test_1D_1D_correlation_multiplicative_model_error.py
tests/integration_tests/tests_with_correlation/test_1D_2D_correlation_additive_model_error.py
tests/integration_tests/tests_with_correlation/test_1D_2D_correlation_multiplicative_model_error.py
tests/integration_tests/tests_with_correlation/test_1D_correlation_additive_model_error.py
tests/integration_tests/tests_with_correlation/test_1D_correlation_additive_model_error_alt_def.py
tests/integration_tests/tests_with_correlation/test_1D_correlation_multiplicative_model_error.py
probeye-3.0.4.dist-info/LICENSE
probeye-3.0.4.dist-info/METADATA
probeye-3.0.4.dist-info/WHEEL
probeye-3.0.4.dist-info/top_level.txt
probeye-3.0.4.dist-info/RECORD
