Metadata-Version: 2.1
Name: probeye
Version: 3.0.4
Summary: A general framework for setting up parameter estimation problems.
Home-page: UNKNOWN
Author: Alexander Klawonn
Author-email: alexander.klawonn@bam.de
License: UNKNOWN
Platform: UNKNOWN
Classifier: Programming Language :: Python :: 3.6
Classifier: Programming Language :: Python :: 3.7
Classifier: Programming Language :: Python :: 3.8
Classifier: Programming Language :: Python :: 3.9
Classifier: Topic :: Scientific/Engineering
Classifier: Intended Audience :: Science/Research
Classifier: Operating System :: OS Independent
Classifier: License :: OSI Approved :: MIT License
Requires-Python: >=3.6
License-File: LICENSE
Requires-Dist: numpy (<2)
Requires-Dist: scipy (<2)
Requires-Dist: matplotlib (<4)
Requires-Dist: emcee (<4)
Requires-Dist: tabulate (<1)
Requires-Dist: arviz (<1)
Requires-Dist: loguru (<1)
Requires-Dist: rdflib (<7)
Requires-Dist: owlready2 (<1)
Requires-Dist: dynesty
Requires-Dist: tri-py (<1)
Provides-Extra: docs
Requires-Dist: sphinx (<5,>=3) ; extra == 'docs'
Requires-Dist: sphinx-gallery (<1) ; extra == 'docs'
Requires-Dist: sphinx-copybutton (<1) ; extra == 'docs'
Requires-Dist: sphinx-inline-tabs ; extra == 'docs'
Requires-Dist: sphinxcontrib-bibtex (<3) ; extra == 'docs'
Requires-Dist: myst-parser (<1) ; extra == 'docs'
Requires-Dist: furo ; extra == 'docs'
Provides-Extra: lint_type_checks
Requires-Dist: pre-commit ; extra == 'lint_type_checks'
Provides-Extra: tests
Requires-Dist: pytest ; extra == 'tests'
Requires-Dist: coverage[toml] ; extra == 'tests'
